fastvid/__init__.py
fastvid/main.py
fastvid/utils.py
fastvid-0.1.7.dist-info/LICENSE
fastvid-0.1.7.dist-info/METADATA
fastvid-0.1.7.dist-info/WHEEL
fastvid-0.1.7.dist-info/entry_points.txt
fastvid-0.1.7.dist-info/top_level.txt
fastvid-0.1.7.dist-info/RECORD
