Metadata-Version: 2.1
Name: fastvid
Version: 0.1.7
Summary: A GUI tool for video processing (acceleration, GIF conversion, compression).
Home-page: https://github.com/yourusername/fastvid
Author: mellon
Author-email: mellon.email@example.com
Classifier: Programming Language :: Python :: 3
Classifier: License :: OSI Approved :: MIT License
Classifier: Operating System :: OS Independent
Requires-Python: >=3.6
License-File: LICENSE
Requires-Dist: customtkinter
